.env
.pep8
MANIFEST.in
Makefile
README.md
README_kr.md
setup.cfg
setup.py
conf/__init__.py
conf/config.json
conf/config_dev.json
docs/email.png
docs/transmission.png
docs/transmissionRESTfulAPI.js
pet/__init__.py
pet/__main__.py
pet.egg-info/PKG-INFO
pet.egg-info/SOURCES.txt
pet.egg-info/dependency_links.txt
pet.egg-info/entry_points.txt
pet.egg-info/not-zip-safe
pet.egg-info/top_level.txt
pet/src/__init__.py
pet/src/daemon.py
pet/src/service.py
pet/src/thread.py
pet/src/controller/__init__.py
pet/src/controller/mail_controller.py
pet/src/controller/transmission_controller.py
pet/test/__init__.py
pet/test/test_config.py
pet/test/test_context.py
pet/test/test_logger.py
pet/test/test_mail_ctrl.py
pet/test/test_trans_ctrl.py
pet/utils/__init__.py
pet/utils/logger.py
pet/utils/config/__init__.py
pet/utils/config/config.py
pet/utils/config/context.py