Metadata-Version: 1.1
Name: pet
Version: 0.3.1
Summary: This program or lib can download torrent file throughemail account and send the torrent file to transmission web controller
Home-page: http://github.com/drake-jin/pi-email-transmission
Author: drakejin
Author-email: dydwls121200@gmail.com
License: MIT
Download-URL: https://github.com/drake-jin/pi-email-transmission/archive/0.3.0.tar.gz
Keywords: torrent transmission rpc email download bittorrent utorrent
Platform: UNKNOWN
Classifier: Development Status :: 3 - Alpha
Classifier: License :: OSI Approved :: MIT License
Classifier: Programming Language :: Python :: 2.6
Classifier: Programming Language :: Python :: 2.7
Classifier: Programming Language :: Python :: 3.2
Classifier: Programming Language :: Python :: 3.3
Classifier: Programming Language :: Python :: 3.4
Classifier: Programming Language :: Python :: 3.5
Classifier: Programming Language :: Python :: 3.6
Classifier: Topic :: Text Processing :: Linguistic
